stonks/__init__.py
pystonks-1.0.dist-info/LICENSE
pystonks-1.0.dist-info/METADATA
pystonks-1.0.dist-info/WHEEL
pystonks-1.0.dist-info/entry_points.txt
pystonks-1.0.dist-info/top_level.txt
pystonks-1.0.dist-info/RECORD
