Metadata-Version: 2.1
Name: pystonks
Version: 1.0
Summary: stonks
Home-page: https://github.com/Hopson97/Stonks/
Author: Hopson97
Author-email: UNKNOWN
License: UNKNOWN
Platform: UNKNOWN
